physiocore/__init__.py
physiocore/_version.py
physiocore/ankle_toe_movement.py
physiocore/any_prone_straight_leg_raise.py
physiocore/any_straight_leg_raise.py
physiocore/bridging.py
physiocore/cobra_stretch.py
physiocore/neck_rotation.py
physiocore/session_assistant.py
physiocore/tracker.py
physiocore/json/ankle_toe_movement.json
physiocore/json/any_prone_straight_leg_raise.json
physiocore/json/any_straight_leg_raise.json
physiocore/json/bridging.json
physiocore/json/cobra_stretch.json
physiocore/json/neck_rotation.json
physiocore/lib/__init__.py
physiocore/lib/basic_math.py
physiocore/lib/exercise_lib.py
physiocore/lib/file_utils.py
physiocore/lib/graphics_utils.py
physiocore/lib/landmark_smoother.py
physiocore/lib/landmark_utils.py
physiocore/lib/modern_flags.py
physiocore/lib/mp_utils.py
physiocore/lib/platform_utils.py
physiocore/lib/timer_utils.py
physiocore/lib/voice_utils.py
physiocore/lib/sounds/DoAnkleToeNow.wav
physiocore/lib/sounds/DoBridgingPoseNow.wav
physiocore/lib/sounds/DoCobraPoseNow.wav
physiocore/lib/sounds/DoNeckRotationNow.wav
physiocore/lib/sounds/DoProneSLRNow.wav
physiocore/lib/sounds/DoSLRNow.wav
physiocore/lib/sounds/EndOfSession.wav
physiocore/lib/sounds/FiveRepeatsCompleted.wav
physiocore/lib/sounds/GreatFormKeepItUp.wav
physiocore/lib/sounds/Hindi-DoAnkleToeNow.wav
physiocore/lib/sounds/Hindi-DoBridgingPoseNow.wav
physiocore/lib/sounds/Hindi-DoCobraPoseNow.wav
physiocore/lib/sounds/Hindi-DoNeckRotationNow.wav
physiocore/lib/sounds/Hindi-DoProneSLRNow.wav
physiocore/lib/sounds/Hindi-DoSLRNow.wav
physiocore/lib/sounds/Hindi-EndOfSession.wav
physiocore/lib/sounds/Hindi-FiveRepeatsCompleted.wav
physiocore/lib/sounds/Hindi-WellDoneTakeQuickRest.wav
physiocore/lib/sounds/Hindi-welcome.wav
physiocore/lib/sounds/Indian-DoAnkleToeNow.wav
physiocore/lib/sounds/Indian-DoBridgingPoseNow.wav
physiocore/lib/sounds/Indian-DoCobraPoseNow.wav
physiocore/lib/sounds/Indian-DoNeckRotationNow.wav
physiocore/lib/sounds/Indian-DoProneSLRNow.wav
physiocore-0.3.5.dist-info/licenses/LICENSE
physiocore-0.3.5.dist-info/licenses/NOTICE
physiocore-0.3.5.dist-info/METADATA
physiocore-0.3.5.dist-info/WHEEL
physiocore-0.3.5.dist-info/top_level.txt
physiocore-0.3.5.dist-info/RECORD
