Metadata-Version: 2.4
Name: physiocore
Version: 0.3.5
Summary: A physiotherapy exercise toolkit with movement scripts, utilities, and resources.
Author-email: Pankaj Maurya <pankajmaurya@gmail.com>
License: Apache License  
Project-URL: Homepage, https://github.com/pankajmaurya/PhysioPlus
Project-URL: Repository, https://github.com/pankajmaurya/PhysioPlus
Keywords: physiotherapy,exercise,movement,rehab
Requires-Python: <=3.11,>=3.10.11
License-File: LICENSE
License-File: NOTICE
Requires-Dist: mediapipe==0.10.21
Requires-Dist: opencv-python<4.12
Requires-Dist: opencv-contrib-python<4.12
Requires-Dist: numpy<2
Requires-Dist: pygame
Requires-Dist: setuptools<81
Dynamic: license-file
